{
  "@context": "https://raw.githubusercontent.com/Ningensei848/ML4Keiba/main/context.jsonld",
  "@id": "horse:2019110039",
  "@type": "ml4keiba:Horse",
  "name": "○外アウトパフォーム",
  "status": "現役",
  "sex": "牡",
  "color": "芦毛",
  "result": null,
  "birthday": "2019/03/11",
  "trainer": {
    "@id": "trainer:01127",
    "@type": "ml4keiba:Trainer",
    "name": "栗田徹"
  },
  "owner": {
    "@id": "owner:003060",
    "@type": "ml4keiba:Owner",
    "name": "ゴドルフィン",
    "silks": "https://cdn.netkeiba.com/img//db/colours/003060.gif"
  },
  "breeder": {
    "@id": "breeder:600739",
    "@type": "ml4keiba:Breeder",
    "name": "Kingston Stud"
  },
  "birthplace": "英",
  "price": null,
  "bounty": 580.0,
  "F": {
    "@id": "horse:000a014fbc",
    "@type": "ml4keiba:Horse",
    "name_ja": null,
    "name_en": "Outstrip"
  },
  "M": {
    "@id": "horse:000a01987c",
    "@type": "ml4keiba:Horse",
    "name_ja": null,
    "name_en": "Triple Cee"
  },
  "FF": {
    "@id": "horse:000a010a61",
    "@type": "ml4keiba:Horse",
    "name_ja": null,
    "name_en": "Exceed And Excel"
  },
  "FM": {
    "@id": "horse:000a01404d",
    "@type": "ml4keiba:Horse",
    "name_ja": null,
    "name_en": "Asi Siempre"
  },
  "MF": {
    "@id": "horse:000a0022ae",
    "@type": "ml4keiba:Horse",
    "name_ja": null,
    "name_en": "Cape Cross"
  },
  "MM": {
    "@id": "horse:000a01987b",
    "@type": "ml4keiba:Horse",
    "name_ja": null,
    "name_en": "Karri Valley"
  },
  "FFF": {
    "@id": "horse:000a0000d1",
    "@type": "ml4keiba:Horse",
    "name_ja": "デインヒル",
    "name_en": "Danehill"
  },
  "FFM": {
    "@id": "horse:000a010a6c",
    "@type": "ml4keiba:Horse",
    "name_ja": null,
    "name_en": "Patrona"
  },
  "FMF": {
    "@id": "horse:000a001fb5",
    "@type": "ml4keiba:Horse",
    "name_ja": null,
    "name_en": "El Prado"
  },
  "FMM": {
    "@id": "horse:000a01404c",
    "@type": "ml4keiba:Horse",
    "name_ja": null,
    "name_en": "Siempre Asi"
  },
  "MFF": {
    "@id": "horse:000a0017d2",
    "@type": "ml4keiba:Horse",
    "name_ja": null,
    "name_en": "Green Desert"
  },
  "MFM": {
    "@id": "horse:000a009fa4",
    "@type": "ml4keiba:Horse",
    "name_ja": null,
    "name_en": "Park Appeal"
  },
  "MMF": {
    "@id": "horse:000a0016d4",
    "@type": "ml4keiba:Horse",
    "name_ja": null,
    "name_en": "Storm Bird"
  },
  "MMM": {
    "@id": "horse:000a009a2e",
    "@type": "ml4keiba:Horse",
    "name_ja": null,
    "name_en": "Lisadell"
  },
  "FFFF": {
    "@id": "horse:000a0000d3",
    "@type": "ml4keiba:Horse",
    "name_ja": null,
    "name_en": "Danzig"
  },
  "FFFM": {
    "@id": "horse:000a009233",
    "@type": "ml4keiba:Horse",
    "name_ja": null,
    "name_en": "Razyana"
  },
  "FFMF": {
    "@id": "horse:000a0016b9",
    "@type": "ml4keiba:Horse",
    "name_ja": null,
    "name_en": "Lomond"
  },
  "FFMM": {
    "@id": "horse:000a009c08",
    "@type": "ml4keiba:Horse",
    "name_ja": null,
    "name_en": "Gladiolus"
  },
  "FMFF": {
    "@id": "horse:000a00185d",
    "@type": "ml4keiba:Horse",
    "name_ja": null,
    "name_en": "Sadler's Wells"
  },
  "FMFM": {
    "@id": "horse:000a00940f",
    "@type": "ml4keiba:Horse",
    "name_ja": null,
    "name_en": "Lady Capulet"
  },
  "FMMF": {
    "@id": "horse:000a0019b4",
    "@type": "ml4keiba:Horse",
    "name_ja": null,
    "name_en": "Silver Hawk"
  },
  "FMMM": {
    "@id": "horse:000a0087da",
    "@type": "ml4keiba:Horse",
    "name_ja": null,
    "name_en": "Turkish Treasure"
  },
  "MFFF": {
    "@id": "horse:000a0000d3",
    "@type": "ml4keiba:Horse",
    "name_ja": null,
    "name_en": "Danzig"
  },
  "MFFM": {
    "@id": "horse:000a008662",
    "@type": "ml4keiba:Horse",
    "name_ja": null,
    "name_en": "Foreign Courier"
  },
  "MFMF": {
    "@id": "horse:000a00176c",
    "@type": "ml4keiba:Horse",
    "name_ja": null,
    "name_en": "Ahonoora"
  },
  "MFMM": {
    "@id": "horse:000a008c3e",
    "@type": "ml4keiba:Horse",
    "name_ja": null,
    "name_en": "Balidaress"
  },
  "MMFF": {
    "@id": "horse:000a000e04",
    "@type": "ml4keiba:Horse",
    "name_ja": null,
    "name_en": "Northern Dancer"
  },
  "MMFM": {
    "@id": "horse:000a00834c",
    "@type": "ml4keiba:Horse",
    "name_ja": null,
    "name_en": "South Ocean"
  },
  "MMMF": {
    "@id": "horse:000a000f12",
    "@type": "ml4keiba:Horse",
    "name_ja": null,
    "name_en": "Forli"
  },
  "MMMM": {
    "@id": "horse:000a007e3f",
    "@type": "ml4keiba:Horse",
    "name_ja": null,
    "name_en": "Thong"
  },
  "FFFFF": {
    "@id": "horse:000a000e04",
    "@type": "ml4keiba:Horse",
    "name_ja": null,
    "name_en": "Northern Dancer"
  },
  "FFFFM": {
    "@id": "horse:000a000491",
    "@type": "ml4keiba:Horse",
    "name_ja": null,
    "name_en": "Pas de Nom"
  },
  "FFFMF": {
    "@id": "horse:000a000628",
    "@type": "ml4keiba:Horse",
    "name_ja": null,
    "name_en": "His Majesty"
  },
  "FFFMM": {
    "@id": "horse:000a00922b",
    "@type": "ml4keiba:Horse",
    "name_ja": null,
    "name_en": "Spring Adieu"
  },
  "FFMFF": {
    "@id": "horse:000a000e04",
    "@type": "ml4keiba:Horse",
    "name_ja": null,
    "name_en": "Northern Dancer"
  },
  "FFMFM": {
    "@id": "horse:000a008080",
    "@type": "ml4keiba:Horse",
    "name_ja": null,
    "name_en": "My Charmer"
  },
  "FFMMF": {
    "@id": "horse:000a001e1b",
    "@type": "ml4keiba:Horse",
    "name_ja": null,
    "name_en": "Watch Your Step"
  },
  "FFMMM": {
    "@id": "horse:000a009c07",
    "@type": "ml4keiba:Horse",
    "name_ja": null,
    "name_en": "Back Britches"
  },
  "FMFFF": {
    "@id": "horse:000a000e04",
    "@type": "ml4keiba:Horse",
    "name_ja": null,
    "name_en": "Northern Dancer"
  },
  "FMFFM": {
    "@id": "horse:000a008892",
    "@type": "ml4keiba:Horse",
    "name_ja": null,
    "name_en": "Fairy Bridge"
  },
  "FMFMF": {
    "@id": "horse:000a000dd9",
    "@type": "ml4keiba:Horse",
    "name_ja": null,
    "name_en": "Sir Ivor"
  },
  "FMFMM": {
    "@id": "horse:000a0081b6",
    "@type": "ml4keiba:Horse",
    "name_ja": null,
    "name_en": "Cap and Bells"
  },
  "FMMFF": {
    "@id": "horse:000a0012cb",
    "@type": "ml4keiba:Horse",
    "name_ja": null,
    "name_en": "Roberto"
  },
  "FMMFM": {
    "@id": "horse:000a008c0e",
    "@type": "ml4keiba:Horse",
    "name_ja": null,
    "name_en": "Gris Vitesse"
  },
  "FMMMF": {
    "@id": "horse:000a000dd9",
    "@type": "ml4keiba:Horse",
    "name_ja": null,
    "name_en": "Sir Ivor"
  },
  "FMMMM": {
    "@id": "horse:000a0082d0",
    "@type": "ml4keiba:Horse",
    "name_ja": null,
    "name_en": "Turban"
  },
  "MFFFF": {
    "@id": "horse:000a000e04",
    "@type": "ml4keiba:Horse",
    "name_ja": null,
    "name_en": "Northern Dancer"
  },
  "MFFFM": {
    "@id": "horse:000a000491",
    "@type": "ml4keiba:Horse",
    "name_ja": null,
    "name_en": "Pas de Nom"
  },
  "MFFMF": {
    "@id": "horse:000a000dd9",
    "@type": "ml4keiba:Horse",
    "name_ja": null,
    "name_en": "Sir Ivor"
  },
  "MFFMM": {
    "@id": "horse:000a008661",
    "@type": "ml4keiba:Horse",
    "name_ja": null,
    "name_en": "Courtly Dee"
  },
  "MFMFF": {
    "@id": "horse:000a000f66",
    "@type": "ml4keiba:Horse",
    "name_ja": null,
    "name_en": "Lorenzaccio"
  },
  "MFMFM": {
    "@id": "horse:000a0084c0",
    "@type": "ml4keiba:Horse",
    "name_ja": null,
    "name_en": "Helen Nichols"
  },
  "MFMMF": {
    "@id": "horse:000a001816",
    "@type": "ml4keiba:Horse",
    "name_ja": null,
    "name_en": "Balidar"
  },
  "MFMMM": {
    "@id": "horse:000a008c3d",
    "@type": "ml4keiba:Horse",
    "name_ja": null,
    "name_en": "Innocence"
  },
  "MMFFF": {
    "@id": "horse:000a000f8c",
    "@type": "ml4keiba:Horse",
    "name_ja": null,
    "name_en": "Nearctic"
  },
  "MMFFM": {
    "@id": "horse:000a00702e",
    "@type": "ml4keiba:Horse",
    "name_ja": null,
    "name_en": "Natalma"
  },
  "MMFMF": {
    "@id": "horse:000a0016d3",
    "@type": "ml4keiba:Horse",
    "name_ja": null,
    "name_en": "New Providence"
  },
  "MMFMM": {
    "@id": "horse:000a00834b",
    "@type": "ml4keiba:Horse",
    "name_ja": null,
    "name_en": "Shining Sun"
  },
  "MMMFF": {
    "@id": "horse:000a001269",
    "@type": "ml4keiba:Horse",
    "name_ja": null,
    "name_en": "Aristophanes"
  },
  "MMMFM": {
    "@id": "horse:000a007b49",
    "@type": "ml4keiba:Horse",
    "name_ja": null,
    "name_en": "Trevisa"
  },
  "MMMMF": {
    "@id": "horse:000a001245",
    "@type": "ml4keiba:Horse",
    "name_ja": null,
    "name_en": "Nantallah"
  },
  "MMMMM": {
    "@id": "horse:000a0079c9",
    "@type": "ml4keiba:Horse",
    "name_ja": null,
    "name_en": "Rough Shod"
  }
}