{
    "title": "高雄特別 ",
    "outer_loop": true,
    "field": "芝",
    "direction": "右",
    "distance": "2400",
    "weather": "曇",
    "going": "不良",
    "start_at": "14:25",
    "date": "2020年10月10日",
    "course_info": "4回京都1日目",
    "requirements": "3歳以上1000万下",
    "rule": "(混)[指](ハンデ)",
    "runner_list": [
        "ディアマンミノル",
        "ピッツィカート",
        "ダンシングリッチー",
        "ドゥラモット",
        "プランドラー",
        "エレヴァルアスール",
        "イチダイ",
        "トウカイデュエル",
        "アルサトワ"
    ],
    "runner": {
        "ディアマンミノル": {
            "horce_id": "2017103174",
            "horse_name": "ディアマンミノル",
            "jockey_id": "01018",
            "jockey_name": "和田竜二",
            "trainer_id": "01099",
            "trainer_name": "本田優",
            "trainer_org": "西",
            "owner_id": "265008",
            "owner_name": "吉岡實"
        },
        "ピッツィカート": {
            "horce_id": "2013105976",
            "horse_name": "ピッツィカート",
            "jockey_id": "01180",
            "jockey_name": "団野大成",
            "trainer_id": "01002",
            "trainer_name": "音無秀孝",
            "trainer_org": "西",
            "owner_id": "506800",
            "owner_name": "シルクレーシング"
        },
        "ダンシングリッチー": {
            "horce_id": "2017104829",
            "horse_name": "ダンシングリッチー",
            "jockey_id": "01126",
            "jockey_name": "松山弘平",
            "trainer_id": "01173",
            "trainer_name": "長谷川浩",
            "trainer_org": "西",
            "owner_id": "102031",
            "owner_name": "米田稔"
        },
        "ドゥラモット": {
            "horce_id": "2017105334",
            "horse_name": "ドゥラモット",
            "jockey_id": "01117",
            "jockey_name": "丸田恭介",
            "trainer_id": "00438",
            "trainer_name": "安田隆行",
            "trainer_org": "西",
            "owner_id": "879800",
            "owner_name": "雅苑興業"
        },
        "プランドラー": {
            "horce_id": "2016104840",
            "horse_name": "プランドラー",
            "jockey_id": "01116",
            "jockey_name": "藤岡康太",
            "trainer_id": "01071",
            "trainer_name": "池江泰寿",
            "trainer_org": "西",
            "owner_id": "226800",
            "owner_name": "サンデーレーシング"
        },
        "エレヴァルアスール": {
            "horce_id": "2016105414",
            "horse_name": "エレヴァルアスール",
            "jockey_id": "01154",
            "jockey_name": "松若風馬",
            "trainer_id": "01111",
            "trainer_name": "鈴木孝志",
            "trainer_org": "西",
            "owner_id": "047803",
            "owner_name": "アスール"
        },
        "イチダイ": {
            "horce_id": "2013103589",
            "horse_name": "イチダイ",
            "jockey_id": "01015",
            "jockey_name": "古川吉洋",
            "trainer_id": "00380",
            "trainer_name": "柄崎孝",
            "trainer_org": "東",
            "owner_id": "020803",
            "owner_name": "三度屋"
        },
        "トウカイデュエル": {
            "horce_id": "2017101146",
            "horse_name": "トウカイデュエル",
            "jockey_id": "01034",
            "jockey_name": "酒井学",
            "trainer_id": "01009",
            "trainer_name": "田所秀孝",
            "trainer_org": "西",
            "owner_id": "695004",
            "owner_name": "内村正則"
        },
        "アルサトワ": {
            "horce_id": "2017106606",
            "horse_name": "アルサトワ",
            "jockey_id": "00732",
            "jockey_name": "幸英明",
            "trainer_id": "01151",
            "trainer_name": "斉藤崇史",
            "trainer_org": "西",
            "owner_id": "003060",
            "owner_name": "ゴドルフィン"
        }
    },
    "ticket_types": [
        "win",
        "place",
        "bracket_quinella",
        "quinella",
        "quinella_place",
        "exacta",
        "trio",
        "tierce"
    ],
    "dividend": {
        "win": {
            "ja-JP": "単勝",
            "official": "3",
            "refund": "330",
            "favorite": "1"
        },
        "place": {
            "ja-JP": "複勝",
            "official": "3/7/2",
            "refund": "140/500/150",
            "favorite": "1/7/2"
        },
        "bracket_quinella": {
            "ja-JP": "枠連",
            "official": "3 - 7",
            "refund": "5350",
            "favorite": "19"
        },
        "quinella": {
            "ja-JP": "馬連",
            "official": "3 - 7",
            "refund": "7320",
            "favorite": "20"
        },
        "quinella_place": {
            "ja-JP": "ワイド",
            "official": "3 - 7/2 - 3/2 - 7",
            "refund": "1,400/300/1,660",
            "favorite": "17/2/19"
        },
        "exacta": {
            "ja-JP": "馬単",
            "official": "3 → 7",
            "refund": "9600",
            "favorite": "34"
        },
        "trio": {
            "ja-JP": "三連複",
            "official": "2 - 3 - 7",
            "refund": "6930",
            "favorite": "26"
        },
        "tierce": {
            "ja-JP": "三連単",
            "official": "3 → 7 → 2",
            "refund": "56960",
            "favorite": "178"
        }
    },
    "order_of_corner": [
        "9-6-8(2,4)5(1,3)7",
        "9-6,8(2,4)5(1,3)7",
        "9,8,6(2,3)(4,5)1-7",
        "8,6(9,3)4(2,1,5)-7"
    ],
    "racetime": {
        "ラップ": "12.6 - 10.5 - 11.9 - 13.0 - 13.6 - 12.4 - 12.4 - 12.7 - 12.2 - 12.1 - 12.2 - 13.2",
        "ペース": "12.6 - 23.1 - 35.0 - 48.0 - 61.6 - 74.0 - 86.4 - 99.1 - 111.3 - 123.4 - 135.6 - 148.8 (35.0-37.5)"
    }
}