{
    "title": "磐梯山特別 ",
    "field": "芝",
    "direction": "右",
    "distance": "2600",
    "weather": "晴",
    "going": "良",
    "start_at": "14:50",
    "date": "2015年10月31日",
    "course_info": "3回福島1日目",
    "requirements": "3歳以上500万下",
    "rule": "(混)(定量)",
    "runner_list": [
        "テンカイチ",
        "マイネルカレッツァ",
        "マスタープラマー",
        "マイネルヴェルス",
        "クインズストーム",
        "アドマイヤロワ",
        "ゴージャスガール",
        "アルマセクレタ",
        "シグナルアロー",
        "アワフレイム",
        "フォワードカール",
        "ジンライムデザイア"
    ],
    "runner": {
        "テンカイチ": {
            "horce_id": "2010101971",
            "horse_name": "テンカイチ",
            "jockey_id": "01061",
            "jockey_name": "大庭和弥",
            "trainer_id": "01134",
            "trainer_name": "高橋文雅",
            "trainer_org": "東",
            "owner_id": "898005",
            "owner_name": "大原詔宏"
        },
        "マイネルカレッツァ": {
            "horce_id": "2012101430",
            "horse_name": "マイネルカレッツァ",
            "jockey_id": "01077",
            "jockey_name": "石橋脩",
            "trainer_id": "01153",
            "trainer_name": "中舘英二",
            "trainer_org": "東",
            "owner_id": "546800",
            "owner_name": "サラブレッドクラブ・ラフィアン"
        },
        "マスタープラマー": {
            "horce_id": "2012103641",
            "horse_name": "マスタープラマー",
            "jockey_id": "01151",
            "jockey_name": "井上敏樹",
            "trainer_id": "00341",
            "trainer_name": "栗田博憲",
            "trainer_org": "東",
            "owner_id": "851009",
            "owner_name": "岡田牧雄"
        },
        "マイネルヴェルス": {
            "horce_id": "2011105241",
            "horse_name": "マイネルヴェルス",
            "jockey_id": "01091",
            "jockey_name": "丹内祐次",
            "trainer_id": "01097",
            "trainer_name": "鹿戸雄一",
            "trainer_org": "東",
            "owner_id": "546800",
            "owner_name": "サラブレッドクラブ・ラフィアン"
        },
        "クインズストーム": {
            "horce_id": "2011102013",
            "horse_name": "クインズストーム",
            "jockey_id": "01092",
            "jockey_name": "津村明秀",
            "trainer_id": "01074",
            "trainer_name": "奥平雅士",
            "trainer_org": "東",
            "owner_id": "896800",
            "owner_name": "クイーンズ・ランチ"
        },
        "アドマイヤロワ": {
            "horce_id": "2012104661",
            "horse_name": "アドマイヤロワ",
            "jockey_id": "01127",
            "jockey_name": "丸山元気",
            "trainer_id": "00362",
            "trainer_name": "橋田満",
            "trainer_org": "西",
            "owner_id": "398002",
            "owner_name": "近藤利一"
        },
        "ゴージャスガール": {
            "horce_id": "2012103146",
            "horse_name": "ゴージャスガール",
            "jockey_id": "01117",
            "jockey_name": "丸田恭介",
            "trainer_id": "01102",
            "trainer_name": "大竹正博",
            "trainer_org": "東",
            "owner_id": "994002",
            "owner_name": "飯田正剛"
        },
        "アルマセクレタ": {
            "horce_id": "2011100778",
            "horse_name": "アルマセクレタ",
            "jockey_id": "01095",
            "jockey_name": "吉田隼人",
            "trainer_id": "01016",
            "trainer_name": "西浦勝一",
            "trainer_org": "西",
            "owner_id": "095700",
            "owner_name": "コウトミックレーシング"
        },
        "シグナルアロー": {
            "horce_id": "2012100114",
            "horse_name": "シグナルアロー",
            "jockey_id": "01134",
            "jockey_name": "嶋田純次",
            "trainer_id": "01038",
            "trainer_name": "手塚貴久",
            "trainer_org": "東",
            "owner_id": "942006",
            "owner_name": "榊原源一郎"
        },
        "アワフレイム": {
            "horce_id": "2011110018",
            "horse_name": "アワフレイム",
            "jockey_id": "01140",
            "jockey_name": "横山和生",
            "trainer_id": "01141",
            "trainer_name": "尾形和幸",
            "trainer_org": "東",
            "owner_id": "851009",
            "owner_name": "岡田牧雄"
        },
        "フォワードカール": {
            "horce_id": "2011104109",
            "horse_name": "フォワードカール",
            "jockey_id": "01128",
            "jockey_name": "川須栄彦",
            "trainer_id": "01119",
            "trainer_name": "田中剛",
            "trainer_org": "東",
            "owner_id": "506800",
            "owner_name": "シルクレーシング"
        },
        "ジンライムデザイア": {
            "horce_id": "2011100627",
            "horse_name": "ジンライムデザイア",
            "jockey_id": "01153",
            "jockey_name": "木幡初也",
            "trainer_id": "00437",
            "trainer_name": "南田美知",
            "trainer_org": "東",
            "owner_id": "768008",
            "owner_name": "飯田総一郎"
        }
    },
    "ticket_types": [
        "win",
        "place",
        "bracket_quinella",
        "quinella",
        "quinella_place",
        "exacta",
        "trio",
        "tierce"
    ],
    "dividend": {
        "win": {
            "ja-JP": "単勝",
            "official": "11",
            "refund": "5940",
            "favorite": "10"
        },
        "place": {
            "ja-JP": "複勝",
            "official": "11/2/5",
            "refund": "1,860/210/470",
            "favorite": "11/4/7"
        },
        "bracket_quinella": {
            "ja-JP": "枠連",
            "official": "2 - 8",
            "refund": "3780",
            "favorite": "12"
        },
        "quinella": {
            "ja-JP": "馬連",
            "official": "2 - 11",
            "refund": "21180",
            "favorite": "41"
        },
        "quinella_place": {
            "ja-JP": "ワイド",
            "official": "2 - 11/5 - 11/2 - 5",
            "refund": "6,490/11,240/1,610",
            "favorite": "44/56/23"
        },
        "exacta": {
            "ja-JP": "馬単",
            "official": "11 → 2",
            "refund": "69560",
            "favorite": "98"
        },
        "trio": {
            "ja-JP": "三連複",
            "official": "2 - 5 - 11",
            "refund": "80210",
            "favorite": "129"
        },
        "tierce": {
            "ja-JP": "三連単",
            "official": "11 → 2 → 5",
            "refund": "718200",
            "favorite": "895"
        }
    },
    "order_of_corner": [
        "8=2-9-11(10,12)(5,6)1(4,3)-7",
        "8,2,9,11,12,10,6,5,1(4,3)-7",
        "8,2(9,11)12(10,6)(5,1,4)3=7",
        "(*8,2)(9,11)(10,12,6)(5,1,4)3=7"
    ],
    "racetime": {
        "ラップ": "13.2 - 11.0 - 11.8 - 12.1 - 12.6 - 12.5 - 13.4 - 13.2 - 11.8 - 11.7 - 12.0 - 11.9 - 12.5",
        "ペース": "13.2 - 24.2 - 36.0 - 48.1 - 60.7 - 73.2 - 86.6 - 99.8 - 111.6 - 123.3 - 135.3 - 147.2 - 159.7 (36.0-36.4)"
    }
}