{
    "@context": "https://raw.githubusercontent.com/Ningensei848/ML4Keiba/main/contexts.jsonld",
    "@id": "race_id:201110020911",
    "@type": "wd:Q3001412",
    "title": "由布院特別",
    "grade": "non graded",
    "track_surface": "ダート",
    "direction": "右",
    "distance": 1700,
    "weather": "晴",
    "going": "良",
    "start_at": "15:40",
    "date": "2011年4月2日",
    "schedule": {
        "round": "2",
        "place": "小倉",
        "days": "9"
    },
    "requirements": "4歳以上1000万下",
    "rule": [
        "混",
        "定量"
    ],
    "movie": "movie_id:201110020911",
    "runner": [
        {
            "@id": "horse_id:2006101140",
            "@type": "wd:Q726",
            "name": "ジョーメテオ",
            "jockey": {
                "@id": "jockey_id:01095",
                "@type": "schema:Person",
                "name": "吉田隼人"
            },
            "trainer": {
                "@id": "trainer_id:00400",
                "@type": "schema:Person",
                "name": "柴田光陽",
                "member_of": "西"
            },
            "owner": {
                "@id": "owner_id:839004",
                "@type": "schema:ProductGroup",
                "name": "上田けい子"
            },
            "uniform_number": 12,
            "gate_number": 6,
            "organism": "牡",
            "age": 5,
            "counterweight": 57,
            "racetime": "1:47.0",
            "race_result": 1,
            "diff_order": "-",
            "rank_at_corner": [
                15,
                9,
                3,
                3
            ],
            "max_speed": 37.3,
            "odds": 3.6,
            "odds_rank": 2,
            "body": {
                "@id": "horse_id:2006101140",
                "run_for": "race_id:201110020911",
                "weight": 502.0,
                "gain": -8.0
            },
            "bounty": 1428.1
        },
        {
            "@id": "horse_id:2004104596",
            "@type": "wd:Q726",
            "name": "メイクアダッシュ",
            "jockey": {
                "@id": "jockey_id:01117",
                "@type": "schema:Person",
                "name": "丸田恭介"
            },
            "trainer": {
                "@id": "trainer_id:00355",
                "@type": "schema:Person",
                "name": "境征勝",
                "member_of": "東"
            },
            "owner": {
                "@id": "owner_id:992800",
                "@type": "schema:ProductGroup",
                "name": "谷岡牧場"
            },
            "uniform_number": 5,
            "gate_number": 3,
            "organism": "牡",
            "age": 7,
            "counterweight": 57,
            "racetime": "1:47.0",
            "race_result": 2,
            "diff_order": "クビ",
            "rank_at_corner": [
                3,
                3,
                4,
                4
            ],
            "max_speed": 37.1,
            "odds": 33.7,
            "odds_rank": 11,
            "body": {
                "@id": "horse_id:2004104596",
                "run_for": "race_id:201110020911",
                "weight": 470.0,
                "gain": 0.0
            },
            "bounty": 566.6
        },
        {
            "@id": "horse_id:2005106900",
            "@type": "wd:Q726",
            "name": "アースマリン",
            "jockey": {
                "@id": "jockey_id:01075",
                "@type": "schema:Person",
                "name": "田辺裕信"
            },
            "trainer": {
                "@id": "trainer_id:00405",
                "@type": "schema:Person",
                "name": "小西一男",
                "member_of": "東"
            },
            "owner": {
                "@id": "owner_id:339008",
                "@type": "schema:ProductGroup",
                "name": "松山増男"
            },
            "uniform_number": 10,
            "gate_number": 5,
            "organism": "牝",
            "age": 6,
            "counterweight": 55,
            "racetime": "1:47.2",
            "race_result": 3,
            "diff_order": "1.1/2",
            "rank_at_corner": [
                6,
                5,
                6,
                4
            ],
            "max_speed": 37.1,
            "odds": 8.2,
            "odds_rank": 4,
            "body": {
                "@id": "horse_id:2005106900",
                "run_for": "race_id:201110020911",
                "weight": 468.0,
                "gain": -16.0
            },
            "bounty": 348.3
        },
        {
            "@id": "horse_id:2004103936",
            "@type": "wd:Q726",
            "name": "サニーラブカフェ",
            "jockey": {
                "@id": "jockey_id:01026",
                "@type": "schema:Person",
                "name": "武幸四郎"
            },
            "trainer": {
                "@id": "trainer_id:01013",
                "@type": "schema:Person",
                "name": "小島太",
                "member_of": "東"
            },
            "owner": {
                "@id": "owner_id:505007",
                "@type": "schema:ProductGroup",
                "name": "西川恭子"
            },
            "uniform_number": 3,
            "gate_number": 2,
            "organism": "牝",
            "age": 7,
            "counterweight": 55,
            "racetime": "1:47.3",
            "race_result": 4,
            "diff_order": "クビ",
            "rank_at_corner": [
                7,
                9,
                7,
                8
            ],
            "max_speed": 36.9,
            "odds": 16.4,
            "odds_rank": 6,
            "body": {
                "@id": "horse_id:2004103936",
                "run_for": "race_id:201110020911",
                "weight": 492.0,
                "gain": -10.0
            },
            "bounty": 210.0
        },
        {
            "@id": "horse_id:2005105159",
            "@type": "wd:Q726",
            "name": "ライコウテンユウ",
            "jockey": {
                "@id": "jockey_id:01128",
                "@type": "schema:Person",
                "name": "川須栄彦"
            },
            "trainer": {
                "@id": "trainer_id:00221",
                "@type": "schema:Person",
                "name": "武宏平",
                "member_of": "西"
            },
            "owner": {
                "@id": "owner_id:249009",
                "@type": "schema:ProductGroup",
                "name": "内田正也"
            },
            "uniform_number": 1,
            "gate_number": 1,
            "organism": "牡",
            "age": 6,
            "counterweight": 57,
            "racetime": "1:47.3",
            "race_result": 5,
            "diff_order": "アタマ",
            "rank_at_corner": [
                1,
                1,
                1,
                1
            ],
            "max_speed": 37.8,
            "odds": 76.4,
            "odds_rank": 13,
            "body": {
                "@id": "horse_id:2005105159",
                "run_for": "race_id:201110020911",
                "weight": 524.0,
                "gain": -6.0
            },
            "bounty": 137.0
        },
        {
            "@id": "horse_id:2007101272",
            "@type": "wd:Q726",
            "name": "スーサンストリーム",
            "jockey": {
                "@id": "jockey_id:01006",
                "@type": "schema:Person",
                "name": "野元昭嘉"
            },
            "trainer": {
                "@id": "trainer_id:00397",
                "@type": "schema:Person",
                "name": "岩元市三",
                "member_of": "西"
            },
            "owner": {
                "@id": "owner_id:043008",
                "@type": "schema:ProductGroup",
                "name": "林千枝子"
            },
            "uniform_number": 8,
            "gate_number": 4,
            "organism": "牡",
            "age": 4,
            "counterweight": 57,
            "racetime": "1:47.5",
            "race_result": 6,
            "diff_order": "1.1/2",
            "rank_at_corner": [
                9,
                9,
                7,
                7
            ],
            "max_speed": 37.2,
            "odds": 34.5,
            "odds_rank": 12,
            "body": {
                "@id": "horse_id:2007101272",
                "run_for": "race_id:201110020911",
                "weight": 454.0,
                "gain": -6.0
            },
            "bounty": 0
        },
        {
            "@id": "horse_id:2006103902",
            "@type": "wd:Q726",
            "name": "ヘリオスシチー",
            "jockey": {
                "@id": "jockey_id:00635",
                "@type": "schema:Person",
                "name": "中舘英二"
            },
            "trainer": {
                "@id": "trainer_id:01066",
                "@type": "schema:Person",
                "name": "岡田稲男",
                "member_of": "西"
            },
            "owner": {
                "@id": "owner_id:321800",
                "@type": "schema:ProductGroup",
                "name": "友駿ホースクラブ"
            },
            "uniform_number": 6,
            "gate_number": 3,
            "organism": "牡",
            "age": 5,
            "counterweight": 57,
            "racetime": "1:47.6",
            "race_result": 7,
            "diff_order": "3/4",
            "rank_at_corner": [
                11,
                3,
                2,
                2
            ],
            "max_speed": 38.0,
            "odds": 7.7,
            "odds_rank": 3,
            "body": {
                "@id": "horse_id:2006103902",
                "run_for": "race_id:201110020911",
                "weight": 454.0,
                "gain": -6.0
            },
            "bounty": 0
        },
        {
            "@id": "horse_id:2006102540",
            "@type": "wd:Q726",
            "name": "ヒカリアスティル",
            "jockey": {
                "@id": "jockey_id:01034",
                "@type": "schema:Person",
                "name": "酒井学"
            },
            "trainer": {
                "@id": "trainer_id:00431",
                "@type": "schema:Person",
                "name": "谷潔",
                "member_of": "西"
            },
            "owner": {
                "@id": "owner_id:741002",
                "@type": "schema:ProductGroup",
                "name": "當山隆則"
            },
            "uniform_number": 7,
            "gate_number": 4,
            "organism": "牡",
            "age": 5,
            "counterweight": 57,
            "racetime": "1:47.8",
            "race_result": 8,
            "diff_order": "1",
            "rank_at_corner": [
                9,
                12,
                12,
                11
            ],
            "max_speed": 37.1,
            "odds": 19.0,
            "odds_rank": 7,
            "body": {
                "@id": "horse_id:2006102540",
                "run_for": "race_id:201110020911",
                "weight": 516.0,
                "gain": 0.0
            },
            "bounty": 0
        },
        {
            "@id": "horse_id:2005100613",
            "@type": "wd:Q726",
            "name": "ベストオブミー",
            "jockey": {
                "@id": "jockey_id:01116",
                "@type": "schema:Person",
                "name": "藤岡康太"
            },
            "trainer": {
                "@id": "trainer_id:01046",
                "@type": "schema:Person",
                "name": "鮫島一歩",
                "member_of": "西"
            },
            "owner": {
                "@id": "owner_id:994002",
                "@type": "schema:ProductGroup",
                "name": "飯田正剛"
            },
            "uniform_number": 13,
            "gate_number": 7,
            "organism": "牝",
            "age": 6,
            "counterweight": 55,
            "racetime": "1:47.8",
            "race_result": 9,
            "diff_order": "アタマ",
            "rank_at_corner": [
                13,
                12,
                10,
                11
            ],
            "max_speed": 37.3,
            "odds": 21.2,
            "odds_rank": 8,
            "body": {
                "@id": "horse_id:2005100613",
                "run_for": "race_id:201110020911",
                "weight": 470.0,
                "gain": 2.0
            },
            "bounty": 0
        },
        {
            "@id": "horse_id:2006101479",
            "@type": "wd:Q726",
            "name": "パープルスター",
            "jockey": {
                "@id": "jockey_id:01130",
                "@type": "schema:Person",
                "name": "高倉稜"
            },
            "trainer": {
                "@id": "trainer_id:00365",
                "@type": "schema:Person",
                "name": "崎山博樹",
                "member_of": "西"
            },
            "owner": {
                "@id": "owner_id:306008",
                "@type": "schema:ProductGroup",
                "name": "松岡隆雄"
            },
            "uniform_number": 9,
            "gate_number": 5,
            "organism": "牝",
            "age": 5,
            "counterweight": 55,
            "racetime": "1:48.0",
            "race_result": 10,
            "diff_order": "1.1/4",
            "rank_at_corner": [
                2,
                2,
                4,
                4
            ],
            "max_speed": 38.2,
            "odds": 30.5,
            "odds_rank": 10,
            "body": {
                "@id": "horse_id:2006101479",
                "run_for": "race_id:201110020911",
                "weight": 490.0,
                "gain": -12.0
            },
            "bounty": 0
        },
        {
            "@id": "horse_id:2004101071",
            "@type": "wd:Q726",
            "name": "アプローズヒーロー",
            "jockey": {
                "@id": "jockey_id:00712",
                "@type": "schema:Person",
                "name": "小林淳一"
            },
            "trainer": {
                "@id": "trainer_id:01043",
                "@type": "schema:Person",
                "name": "石栗龍彦",
                "member_of": "東"
            },
            "owner": {
                "@id": "owner_id:212008",
                "@type": "schema:ProductGroup",
                "name": "小野博郷"
            },
            "uniform_number": 14,
            "gate_number": 7,
            "organism": "牡",
            "age": 7,
            "counterweight": 57,
            "racetime": "1:48.0",
            "race_result": 11,
            "diff_order": "ハナ",
            "rank_at_corner": [
                14,
                14,
                14,
                14
            ],
            "max_speed": 37.2,
            "odds": 324.6,
            "odds_rank": 16,
            "body": {
                "@id": "horse_id:2004101071",
                "run_for": "race_id:201110020911",
                "weight": 446.0,
                "gain": -12.0
            },
            "bounty": 0
        },
        {
            "@id": "horse_id:2007101483",
            "@type": "wd:Q726",
            "name": "レオキュート",
            "jockey": {
                "@id": "jockey_id:01096",
                "@type": "schema:Person",
                "name": "大野拓弥"
            },
            "trainer": {
                "@id": "trainer_id:00377",
                "@type": "schema:Person",
                "name": "平井雄二",
                "member_of": "東"
            },
            "owner": {
                "@id": "owner_id:209800",
                "@type": "schema:ProductGroup",
                "name": "レオ"
            },
            "uniform_number": 2,
            "gate_number": 1,
            "organism": "牝",
            "age": 4,
            "counterweight": 55,
            "racetime": "1:48.0",
            "race_result": 12,
            "diff_order": "クビ",
            "rank_at_corner": [
                11,
                14,
                14,
                14
            ],
            "max_speed": 37.1,
            "odds": 22.6,
            "odds_rank": 9,
            "body": {
                "@id": "horse_id:2007101483",
                "run_for": "race_id:201110020911",
                "weight": 432.0,
                "gain": -10.0
            },
            "bounty": 0
        },
        {
            "@id": "horse_id:2007103343",
            "@type": "wd:Q726",
            "name": "ビーチランデブー",
            "jockey": {
                "@id": "jockey_id:01127",
                "@type": "schema:Person",
                "name": "丸山元気"
            },
            "trainer": {
                "@id": "trainer_id:01011",
                "@type": "schema:Person",
                "name": "松田国英",
                "member_of": "西"
            },
            "owner": {
                "@id": "owner_id:708800",
                "@type": "schema:ProductGroup",
                "name": "金子真人ホールディングス"
            },
            "uniform_number": 11,
            "gate_number": 6,
            "organism": "牡",
            "age": 4,
            "counterweight": 57,
            "racetime": "1:48.1",
            "race_result": 13,
            "diff_order": "1/2",
            "rank_at_corner": [
                15,
                16,
                12,
                9
            ],
            "max_speed": 37.4,
            "odds": 11.0,
            "odds_rank": 5,
            "body": {
                "@id": "horse_id:2007103343",
                "run_for": "race_id:201110020911",
                "weight": 458.0,
                "gain": 2.0
            },
            "bounty": 0
        },
        {
            "@id": "horse_id:2007105248",
            "@type": "wd:Q726",
            "name": "ダノントレビアン",
            "jockey": {
                "@id": "jockey_id:01126",
                "@type": "schema:Person",
                "name": "松山弘平"
            },
            "trainer": {
                "@id": "trainer_id:01092",
                "@type": "schema:Person",
                "name": "松永幹夫",
                "member_of": "西"
            },
            "owner": {
                "@id": "owner_id:619800",
                "@type": "schema:ProductGroup",
                "name": "ダノックス"
            },
            "uniform_number": 15,
            "gate_number": 8,
            "organism": "牡",
            "age": 4,
            "counterweight": 57,
            "racetime": "1:48.2",
            "race_result": 14,
            "diff_order": "1/2",
            "rank_at_corner": [
                4,
                5,
                7,
                9
            ],
            "max_speed": 37.9,
            "odds": 3.2,
            "odds_rank": 1,
            "body": {
                "@id": "horse_id:2007105248",
                "run_for": "race_id:201110020911",
                "weight": 488.0,
                "gain": 2.0
            },
            "bounty": 0
        },
        {
            "@id": "horse_id:2006103691",
            "@type": "wd:Q726",
            "name": "フェイズシフト",
            "jockey": {
                "@id": "jockey_id:01037",
                "@type": "schema:Person",
                "name": "太宰啓介"
            },
            "trainer": {
                "@id": "trainer_id:01040",
                "@type": "schema:Person",
                "name": "服部利之",
                "member_of": "西"
            },
            "owner": {
                "@id": "owner_id:988005",
                "@type": "schema:ProductGroup",
                "name": "吉田修"
            },
            "uniform_number": 16,
            "gate_number": 8,
            "organism": "牝",
            "age": 5,
            "counterweight": 55,
            "racetime": "1:48.3",
            "race_result": 15,
            "diff_order": "クビ",
            "rank_at_corner": [
                7,
                8,
                10,
                11
            ],
            "max_speed": 37.8,
            "odds": 93.6,
            "odds_rank": 14,
            "body": {
                "@id": "horse_id:2006103691",
                "run_for": "race_id:201110020911",
                "weight": 460.0,
                "gain": -6.0
            },
            "bounty": 0
        },
        {
            "@id": "horse_id:2006102367",
            "@type": "wd:Q726",
            "name": "クリノサンデーママ",
            "jockey": {
                "@id": "jockey_id:01062",
                "@type": "schema:Person",
                "name": "川島信二"
            },
            "trainer": {
                "@id": "trainer_id:01030",
                "@type": "schema:Person",
                "name": "星野忍",
                "member_of": "東"
            },
            "owner": {
                "@id": "owner_id:970006",
                "@type": "schema:ProductGroup",
                "name": "栗本博晴"
            },
            "uniform_number": 4,
            "gate_number": 2,
            "organism": "牝",
            "age": 5,
            "counterweight": 55,
            "racetime": "1:49.1",
            "race_result": 16,
            "diff_order": "5",
            "rank_at_corner": [
                4,
                5,
                16,
                16
            ],
            "max_speed": 37.6,
            "odds": 213.3,
            "odds_rank": 15,
            "body": {
                "@id": "horse_id:2006102367",
                "run_for": "race_id:201110020911",
                "weight": 436.0,
                "gain": -6.0
            },
            "bounty": 0
        }
    ],
    "dividend": [
        {
            "@id": "win:_201110020911",
            "@type": "baken:win",
            "name": "単勝",
            "official": "12",
            "refund": "360",
            "odds_rank": "2"
        },
        {
            "@id": "place:_201110020911",
            "@type": "baken:place",
            "name": "複勝",
            "official": "12",
            "refund": "190",
            "odds_rank": "2"
        },
        {
            "@id": "place:_201110020911",
            "@type": "baken:place",
            "name": "複勝",
            "official": "5",
            "refund": "560",
            "odds_rank": "10"
        },
        {
            "@id": "place:_201110020911",
            "@type": "baken:place",
            "name": "複勝",
            "official": "10",
            "refund": "240",
            "odds_rank": "4"
        },
        {
            "@id": "bracket_quinella:_201110020911",
            "@type": "baken:bracket_quinella",
            "name": "枠連",
            "official": "3-6",
            "refund": "910",
            "odds_rank": "4"
        },
        {
            "@id": "quinella:_201110020911",
            "@type": "baken:quinella",
            "name": "馬連",
            "official": "5-12",
            "refund": "7810",
            "odds_rank": "30"
        },
        {
            "@id": "quinella_place:_201110020911",
            "@type": "baken:quinella_place",
            "name": "ワイド",
            "official": "5-12",
            "refund": "2,450",
            "odds_rank": "35"
        },
        {
            "@id": "quinella_place:_201110020911",
            "@type": "baken:quinella_place",
            "name": "ワイド",
            "official": "10-12",
            "refund": "660",
            "odds_rank": "4"
        },
        {
            "@id": "quinella_place:_201110020911",
            "@type": "baken:quinella_place",
            "name": "ワイド",
            "official": "5-10",
            "refund": "3,140",
            "odds_rank": "44"
        },
        {
            "@id": "exacta:_201110020911",
            "@type": "baken:exacta",
            "name": "馬単",
            "official": "12=>5",
            "refund": "11420",
            "odds_rank": "40"
        },
        {
            "@id": "trio:_201110020911",
            "@type": "baken:trio",
            "name": "三連複",
            "official": "5-10-12",
            "refund": "15710",
            "odds_rank": "54"
        },
        {
            "@id": "tierce:_201110020911",
            "@type": "baken:tierce",
            "name": "三連単",
            "official": "12=>5=>10",
            "refund": "81240",
            "odds_rank": "267"
        }
    ],
    "spacing_on_corner": [
        "1,9,5(4,15)10(3,16)(7,8)(2,6)-13-14(11,12)",
        "1,9(5,6)(4,10,15)16(3,8,12)(7,13)(2,14)11",
        "(*1,6)12(9,5)10(3,15,8)(13,16)(7,11)(2,14)-4",
        "(*1,6)12(9,10,5)8,3(15,11)(7,13,16)(2,14)-4"
    ],
    "lap": "7.1 - 11.5 - 12.6 - 13.8 - 12.2 - 12.3 - 12.6 - 12.5 - 12.4",
    "pacemaker": "7.1 - 18.6 - 31.2 - 45.0 - 57.2 - 69.5 - 82.1 - 94.6 - 107.0 (31.2-37.5)"
}