{
  "@context": "https://raw.githubusercontent.com/Ningensei848/ML4Keiba/main/context.jsonld",
  "@id": "horse:2011105253",
  "@type": "ml4keiba:Horse",
  "name": "□地ベルモントナイト",
  "status": null,
  "sex": "牝11歳",
  "color": "鹿毛",
  "result": {
    "first": "13",
    "second": "10",
    "third": "16",
    "others": "87"
  },
  "birthday": "2011/03/04",
  "trainer": {
    "@id": "trainer:a023d",
    "@type": "ml4keiba:Trainer",
    "name": "佐藤祐司"
  },
  "owner": {
    "@id": "owner:x0a03e",
    "@type": "ml4keiba:Owner",
    "name": "Ｉレーシング（株）",
    "silks": "https://cdn.netkeiba.com/img//db/colours/no_data.gif"
  },
  "breeder": {
    "@id": "breeder:800514",
    "@type": "ml4keiba:Breeder",
    "name": "ベルモントファーム"
  },
  "birthplace": "新冠町",
  "price": null,
  "bounty": 2194.0,
  "F": {
    "@id": "horse:1999100226",
    "@type": "ml4keiba:Horse",
    "name_ja": "タニノギムレット",
    "name_en": null
  },
  "M": {
    "@id": "horse:1996101662",
    "@type": "ml4keiba:Horse",
    "name_ja": "スターリーナイト",
    "name_en": null
  },
  "FF": {
    "@id": "horse:000a000082",
    "@type": "ml4keiba:Horse",
    "name_ja": "ブライアンズタイム",
    "name_en": "Brian's Time"
  },
  "FM": {
    "@id": "horse:1988105774",
    "@type": "ml4keiba:Horse",
    "name_ja": "タニノクリスタル",
    "name_en": null
  },
  "MF": {
    "@id": "horse:1988109108",
    "@type": "ml4keiba:Horse",
    "name_ja": "スターオブコジーン",
    "name_en": "Star of Cozzene"
  },
  "MM": {
    "@id": "horse:000a006387",
    "@type": "ml4keiba:Horse",
    "name_ja": "ウィシングフォーアスター",
    "name_en": "Wishing for a Star"
  },
  "FFF": {
    "@id": "horse:000a0012cb",
    "@type": "ml4keiba:Horse",
    "name_ja": null,
    "name_en": "Roberto"
  },
  "FFM": {
    "@id": "horse:000a00877c",
    "@type": "ml4keiba:Horse",
    "name_ja": null,
    "name_en": "Kelley's Day"
  },
  "FMF": {
    "@id": "horse:000a000819",
    "@type": "ml4keiba:Horse",
    "name_ja": "クリスタルパレス",
    "name_en": "Crystal Palace"
  },
  "FMM": {
    "@id": "horse:000a0007bf",
    "@type": "ml4keiba:Horse",
    "name_ja": "タニノシーバード",
    "name_en": "Tanino Sea-Bird"
  },
  "MFF": {
    "@id": "horse:000a001bda",
    "@type": "ml4keiba:Horse",
    "name_ja": null,
    "name_en": "Cozzene"
  },
  "MFM": {
    "@id": "horse:000a009781",
    "@type": "ml4keiba:Horse",
    "name_ja": null,
    "name_en": "Star Gem"
  },
  "MMF": {
    "@id": "horse:000a001607",
    "@type": "ml4keiba:Horse",
    "name_ja": null,
    "name_en": "Mr. Prospector"
  },
  "MMM": {
    "@id": "horse:000a009378",
    "@type": "ml4keiba:Horse",
    "name_ja": null,
    "name_en": "Barbs Dancer"
  },
  "FFFF": {
    "@id": "horse:000a000f2b",
    "@type": "ml4keiba:Horse",
    "name_ja": null,
    "name_en": "Hail to Reason"
  },
  "FFFM": {
    "@id": "horse:000a007c38",
    "@type": "ml4keiba:Horse",
    "name_ja": null,
    "name_en": "Bramalea"
  },
  "FFMF": {
    "@id": "horse:000a001220",
    "@type": "ml4keiba:Horse",
    "name_ja": null,
    "name_en": "Graustark"
  },
  "FFMM": {
    "@id": "horse:000a007c8c",
    "@type": "ml4keiba:Horse",
    "name_ja": null,
    "name_en": "Golden Trail"
  },
  "FMFF": {
    "@id": "horse:000a0010ed",
    "@type": "ml4keiba:Horse",
    "name_ja": null,
    "name_en": "Caro"
  },
  "FMFM": {
    "@id": "horse:000a007f7e",
    "@type": "ml4keiba:Horse",
    "name_ja": null,
    "name_en": "Hermieres"
  },
  "FMMF": {
    "@id": "horse:000a0004bb",
    "@type": "ml4keiba:Horse",
    "name_ja": null,
    "name_en": "Sea-Bird"
  },
  "FMMM": {
    "@id": "horse:000a006fdc",
    "@type": "ml4keiba:Horse",
    "name_ja": null,
    "name_en": "Flaxen"
  },
  "MFFF": {
    "@id": "horse:000a0010ed",
    "@type": "ml4keiba:Horse",
    "name_ja": null,
    "name_en": "Caro"
  },
  "MFFM": {
    "@id": "horse:000a008e45",
    "@type": "ml4keiba:Horse",
    "name_ja": null,
    "name_en": "Ride the Trails"
  },
  "MFMF": {
    "@id": "horse:000a0010f3",
    "@type": "ml4keiba:Horse",
    "name_ja": null,
    "name_en": "Pia Star"
  },
  "MFMM": {
    "@id": "horse:000a009780",
    "@type": "ml4keiba:Horse",
    "name_ja": null,
    "name_en": "Soonerland"
  },
  "MMFF": {
    "@id": "horse:000a000e46",
    "@type": "ml4keiba:Horse",
    "name_ja": null,
    "name_en": "Raise a Native"
  },
  "MMFM": {
    "@id": "horse:000a007e0c",
    "@type": "ml4keiba:Horse",
    "name_ja": null,
    "name_en": "Gold Digger"
  },
  "MMMF": {
    "@id": "horse:000a000e04",
    "@type": "ml4keiba:Horse",
    "name_ja": null,
    "name_en": "Northern Dancer"
  },
  "MMMM": {
    "@id": "horse:000a009377",
    "@type": "ml4keiba:Horse",
    "name_ja": null,
    "name_en": "Periodista"
  },
  "FFFFF": {
    "@id": "horse:000a001042",
    "@type": "ml4keiba:Horse",
    "name_ja": null,
    "name_en": "Turn-to"
  },
  "FFFFM": {
    "@id": "horse:000a0078a6",
    "@type": "ml4keiba:Horse",
    "name_ja": null,
    "name_en": "Nothirdchance"
  },
  "FFFMF": {
    "@id": "horse:000a000f87",
    "@type": "ml4keiba:Horse",
    "name_ja": null,
    "name_en": "Nashua"
  },
  "FFFMM": {
    "@id": "horse:000a007d0b",
    "@type": "ml4keiba:Horse",
    "name_ja": null,
    "name_en": "Rarelea"
  },
  "FFMFF": {
    "@id": "horse:000a000fdf",
    "@type": "ml4keiba:Horse",
    "name_ja": null,
    "name_en": "Ribot"
  },
  "FFMFM": {
    "@id": "horse:000a0075ab",
    "@type": "ml4keiba:Horse",
    "name_ja": null,
    "name_en": "Flower Bowl"
  },
  "FFMMF": {
    "@id": "horse:000a000e21",
    "@type": "ml4keiba:Horse",
    "name_ja": null,
    "name_en": "Hasty Road"
  },
  "FFMMM": {
    "@id": "horse:000a007d3a",
    "@type": "ml4keiba:Horse",
    "name_ja": null,
    "name_en": "Sunny Vale"
  },
  "FMFFF": {
    "@id": "horse:000a000133",
    "@type": "ml4keiba:Horse",
    "name_ja": "フォルティノ",
    "name_en": null
  },
  "FMFFM": {
    "@id": "horse:000a0069ad",
    "@type": "ml4keiba:Horse",
    "name_ja": null,
    "name_en": "Chambord"
  },
  "FMFMF": {
    "@id": "horse:000a000ffd",
    "@type": "ml4keiba:Horse",
    "name_ja": null,
    "name_en": "Sicambre"
  },
  "FMFMM": {
    "@id": "horse:000a007f7d",
    "@type": "ml4keiba:Horse",
    "name_ja": null,
    "name_en": "Vieille Pierre"
  },
  "FMMFF": {
    "@id": "horse:000a000ece",
    "@type": "ml4keiba:Horse",
    "name_ja": null,
    "name_en": "Dan Cupid"
  },
  "FMMFM": {
    "@id": "horse:000a007a3c",
    "@type": "ml4keiba:Horse",
    "name_ja": null,
    "name_en": "Sicalade"
  },
  "FMMMF": {
    "@id": "horse:000a001220",
    "@type": "ml4keiba:Horse",
    "name_ja": null,
    "name_en": "Graustark"
  },
  "FMMMM": {
    "@id": "horse:000a0075a2",
    "@type": "ml4keiba:Horse",
    "name_ja": null,
    "name_en": "Flavia"
  },
  "MFFFF": {
    "@id": "horse:000a000133",
    "@type": "ml4keiba:Horse",
    "name_ja": "フォルティノ",
    "name_en": null
  },
  "MFFFM": {
    "@id": "horse:000a0069ad",
    "@type": "ml4keiba:Horse",
    "name_ja": null,
    "name_en": "Chambord"
  },
  "MFFMF": {
    "@id": "horse:000a000fc7",
    "@type": "ml4keiba:Horse",
    "name_ja": null,
    "name_en": "Prince John"
  },
  "MFFMM": {
    "@id": "horse:000a007070",
    "@type": "ml4keiba:Horse",
    "name_ja": null,
    "name_en": "Wildwook"
  },
  "MFMFF": {
    "@id": "horse:000a000f9f",
    "@type": "ml4keiba:Horse",
    "name_ja": null,
    "name_en": "Olympia"
  },
  "MFMFM": {
    "@id": "horse:000a007c9d",
    "@type": "ml4keiba:Horse",
    "name_ja": null,
    "name_en": "Inquisitive"
  },
  "MFMMF": {
    "@id": "horse:000a000f0e",
    "@type": "ml4keiba:Horse",
    "name_ja": null,
    "name_en": "Fleet Nasrullah"
  },
  "MFMMM": {
    "@id": "horse:000a00977f",
    "@type": "ml4keiba:Horse",
    "name_ja": null,
    "name_en": "Hill Indian"
  },
  "MMFFF": {
    "@id": "horse:000a000f89",
    "@type": "ml4keiba:Horse",
    "name_ja": null,
    "name_en": "Native Dancer"
  },
  "MMFFM": {
    "@id": "horse:000a007984",
    "@type": "ml4keiba:Horse",
    "name_ja": null,
    "name_en": "Raise You"
  },
  "MMFMF": {
    "@id": "horse:000a000f87",
    "@type": "ml4keiba:Horse",
    "name_ja": null,
    "name_en": "Nashua"
  },
  "MMFMM": {
    "@id": "horse:000a007d1c",
    "@type": "ml4keiba:Horse",
    "name_ja": null,
    "name_en": "Sequence"
  },
  "MMMFF": {
    "@id": "horse:000a000f8c",
    "@type": "ml4keiba:Horse",
    "name_ja": null,
    "name_en": "Nearctic"
  },
  "MMMFM": {
    "@id": "horse:000a00702e",
    "@type": "ml4keiba:Horse",
    "name_ja": null,
    "name_en": "Natalma"
  },
  "MMMMF": {
    "@id": "horse:000a000e78",
    "@type": "ml4keiba:Horse",
    "name_ja": null,
    "name_en": "Barbizon"
  },
  "MMMMM": {
    "@id": "horse:000a009376",
    "@type": "ml4keiba:Horse",
    "name_ja": null,
    "name_en": "Swooning"
  }
}